{
  "updated_at": "2026-07-13T12:23:26.391964+08:00",
  "spot": {
    "usd_per_oz": 4049.6,
    "usd_hkd": 7.84,
    "hkd_per_gram": 1020.75,
    "hkd_per_tael": 38205.61
  },
  "retailers": {
    "ctf": {
      "name": "周大福",
      "url": "https://www.chowtaifook.com/zh-hk/eshop/realtime-gold-price.html",
      "updated_time": "2026-07-13 09:24:03",
      "飾金": {
        "賣出_克": 1229.0,
        "賣出_兩": 46000.0,
        "買入_克": 999.0,
        "買入_兩": 37392.0
      },
      "金粒": {
        "賣出_克": 1102.0,
        "賣出_兩": 41247.0,
        "買入_克": 1005.0,
        "買入_兩": 37616.0
      },
      "scraped_at": "2026-07-13T12:23:20.711586+08:00"
    },
    "css": {
      "name": "周生生",
      "url": "https://www.chowsangsang.com/tc/gold-price",
      "updated_time": "13/07/2026 11:20:00",
      "飾金": {
        "賣出_克": 1229.0,
        "賣出_兩": 46000.0,
        "買入_克": 999.0,
        "買入_兩": 37400.0
      },
      "金粒": {
        "賣出_克": 1096.0,
        "賣出_兩": 41000.0,
        "買入_克": 998.0,
        "買入_兩": 37390.0
      },
      "scraped_at": "2026-07-13T12:23:24.228686+08:00"
    },
    "lf": {
      "name": "六福珠寶",
      "url": "https://www.lukfook.com/zh-hk/gold-price",
      "updated_time": "",
      "飾金": {
        "賣出_克": 1228.9,
        "賣出_兩": 45996.0,
        "買入_克": 999.2,
        "買入_兩": 37399.0
      },
      "金粒": {
        "賣出_克": 1095.4,
        "賣出_兩": 41000.0,
        "買入_克": 999.0,
        "買入_兩": 37392.0
      },
      "scraped_at": "2026-07-13T12:23:25.314219+08:00"
    }
  }
}