{
  "updated_at": "2026-05-01T16:14:10.219431+08:00",
  "spot": {
    "usd_per_oz": 4573.2,
    "usd_hkd": 7.833,
    "hkd_per_gram": 1151.7,
    "hkd_per_tael": 43106.95
  },
  "retailers": {
    "ctf": {
      "name": "周大福",
      "url": "https://www.chowtaifook.com/zh-hk/eshop/realtime-gold-price.html",
      "updated_time": "2026-05-01 15:06:02",
      "飾金": {
        "賣出_克": 1389.83,
        "賣出_兩": 52020.0,
        "買入_克": 1111.97,
        "買入_兩": 41620.0
      },
      "金粒": {
        "賣出_克": 1239.15,
        "賣出_兩": 46380.0,
        "買入_克": 1129.87,
        "買入_兩": 42290.0
      },
      "scraped_at": "2026-05-01T16:14:07.030298+08:00"
    },
    "css": {
      "name": "周生生",
      "url": "https://www.chowsangsang.com/tc/gold-price",
      "updated_time": "01/05/2026 14:45:00",
      "飾金": {
        "賣出_克": 1390.0,
        "賣出_兩": 52020.0,
        "買入_克": 1111.0,
        "買入_兩": 41620.0
      },
      "金粒": {
        "賣出_克": 1239.0,
        "賣出_兩": 46370.0,
        "買入_克": 1129.0,
        "買入_兩": 42290.0
      },
      "scraped_at": "2026-05-01T16:14:08.353583+08:00"
    },
    "lf": {
      "name": "六福珠寶",
      "url": "https://www.lukfook.com/zh-hk/gold-price",
      "updated_time": "",
      "飾金": {
        "賣出_克": 1389.8,
        "賣出_兩": 52019.0,
        "買入_克": 1125.3,
        "買入_兩": 42119.0
      },
      "金粒": {
        "賣出_克": 1238.8,
        "賣出_兩": 46367.0,
        "買入_克": 1129.9,
        "買入_兩": 42291.0
      },
      "scraped_at": "2026-05-01T16:14:09.479508+08:00"
    }
  }
}